trainer/__init__.py
trainer/config.py
trainer/events.py
trainer/handlers.py
trainer/mixins.py
trainer/trainer.py
trainer/utils.py
pt_trainer-0.1.9.dist-info/LICENSE
pt_trainer-0.1.9.dist-info/METADATA
pt_trainer-0.1.9.dist-info/WHEEL
pt_trainer-0.1.9.dist-info/top_level.txt
pt_trainer-0.1.9.dist-info/RECORD
