Metadata-Version: 2.1
Name: pt-trainer
Version: 0.1.9
Summary: A toolkit for training pytorch models
Home-page: https://github.com/IljaManakov/PyTorch-Trainer
Author: Ilja Manakov
Author-email: ilja.manakov@gmx.de
License: UNKNOWN
Platform: UNKNOWN
Classifier: Programming Language :: Python :: 3.6
Classifier: License :: OSI Approved :: MIT License
Classifier: Operating System :: OS Independent
